README.md
setup.py
bwh/__init__.py
bwh.egg-info/PKG-INFO
bwh.egg-info/SOURCES.txt
bwh.egg-info/dependency_links.txt
bwh.egg-info/requires.txt
bwh.egg-info/top_level.txt