Metadata-Version: 2.1
Name: bwh
Version: 0.0.1
Summary: bandwagonhost panel api sdk
Home-page: https://github.com/anshengme/bwh
Author: ansheng
Author-email: ianshengme@gmail.com
License: LICENSE
Platform: UNKNOWN
Classifier: Programming Language :: Python :: 3
Classifier: License :: OSI Approved :: MIT License
Classifier: Operating System :: OS Independent
